Metadata-Version: 1.1
Name: scoop
Version: 0.7.1.release
Summary: Scalable COncurrent Operations in Python
Home-page: http://scoop.googlecode.com
Author: SCOOP Development Team
Author-email: scoop-users@googlegroups.com
License: LGPL
Download-URL: http://code.google.com/p/scoop/downloads/list
Keywords: distributed algorithms,parallel programming,Concurrency,Cluster programming,greenlet,zmq
Platform: any
Classifier: Development Status :: 4 - Beta
Classifier: Intended Audience :: Developers
Classifier: Intended Audience :: Education
Classifier: Intended Audience :: Science/Research
Classifier: License :: OSI Approved :: GNU Library or Lesser General Public License (LGPL)
Classifier: Programming Language :: Python
Classifier: Topic :: Scientific/Engineering
Classifier: Topic :: Software Development
